README.txt
setup.cfg
setup.py
stabledict.py
test_stabledict.py
StableDict.egg-info/PKG-INFO
StableDict.egg-info/SOURCES.txt
StableDict.egg-info/dependency_links.txt
StableDict.egg-info/top_level.txt
StableDict.egg-info/zip-safe