Metadata-Version: 1.0
Name: StableDict
Version: 0.2
Summary: A dict subclass which remembers insertion order
Home-page: UNKNOWN
Author: Martin Kammerhofer
Author-email: mkamm@gmx.net
License: PSF
Platform: UNKNOWN
